{
"match_id": 5915014243,
"barracks_status_dire": 63,
"barracks_status_radiant": 0,
"chat": null,
"cluster": 251,
"cosmetics": null,
"dire_score": 43,
"dire_team_id": null,
"draft_timings": null,
"duration": 2343,
"engine": 1,
"first_blood_time": 0,
"game_mode": 22,
"human_players": 10,
"leagueid": 0,
"lobby_type": 7,
"match_seq_num": 4962416559,
"negative_votes": 0,
"objectives": null,
"picks_bans": [
{
"is_pick": true,
"hero_id": 68,
"team": 0,
"order": 0
},
{
"is_pick": true,
"hero_id": 14,
"team": 0,
"order": 1
},
{
"is_pick": true,
"hero_id": 100,
"team": 1,
"order": 2
},
{
"is_pick": true,
"hero_id": 27,
"team": 1,
"order": 3
},
{
"is_pick": true,
"hero_id": 1,
"team": 1,
"order": 4
},
{
"is_pick": true,
"hero_id": 26,
"team": 1,
"order": 5
},
{
"is_pick": true,
"hero_id": 72,
"team": 0,
"order": 6
},
{
"is_pick": true,
"hero_id": 74,
"team": 0,
"order": 7
},
{
"is_pick": true,
"hero_id": 8,
"team": 0,
"order": 8
},
{
"is_pick": true,
"hero_id": 23,
"team": 1,
"order": 9
},
{
"is_pick": false,
"hero_id": 126,
"team": 0,
"order": 10
},
{
"is_pick": false,
"hero_id": 38,
"team": 0,
"order": 11
},
{
"is_pick": false,
"hero_id": 41,
"team": 0,
"order": 12
},
{
"is_pick": false,
"hero_id": 34,
"team": 0,
"order": 13
},
{
"is_pick": false,
"hero_id": 2,
"team": 0,
"order": 14
},
{
"is_pick": false,
"hero_id": 73,
"team": 1,
"order": 15
}
],
"positive_votes": 0,
"radiant_gold_adv": null,
"radiant_score": 36,
"radiant_team_id": null,
"radiant_win": false,
"radiant_xp_adv": null,
"skill": 1,
"start_time": 1616976674,
"teamfights": null,
"tower_status_dire": 2038,
"tower_status_radiant": 0,
"version": null,
"replay_salt": 1182407340,
"series_id": 0,
"series_type": 0,
"players": [
{
"match_id": 5915014243,
"player_slot": 0,
"ability_targets": null,
"ability_upgrades_arr": [
5361,
5362,
5361,
5363,
5361,
5364,
5361,
5363,
5363,
487,
5363,
5364,
5362,
5362,
6653,
5362,
5364,
6652,
6654
],
"ability_uses": null,
"account_id": 253783913,
"actions": null,
"additional_units": null,
"assists": 8,
"backpack_0": 0,
"backpack_1": 51,
"backpack_2": 0,
"backpack_3": null,
"buyback_log": null,
"camps_stacked": null,
"connection_log": null,
"creeps_stacked": null,
"damage": null,
"damage_inflictor": null,
"damage_inflictor_received": null,
"damage_taken": null,
"damage_targets": null,
"deaths": 7,
"denies": 7,
"dn_t": null,
"firstblood_claimed": null,
"gold": 359,
"gold_per_min": 566,
"gold_reasons": null,
"gold_spent": 21430,
"gold_t": null,
"hero_damage": 35949,
"hero_healing": 0,
"hero_hits": null,
"hero_id": 72,
"item_0": 149,
"item_1": 156,
"item_2": 108,
"item_3": 75,
"item_4": 116,
"item_5": 50,
"item_neutral": 334,
"item_uses": null,
"kill_streaks": null,
"killed": null,
"killed_by": null,
"kills": 14,
"kills_log": null,
"lane_pos": null,
"last_hits": 329,
"leaver_status": 0,
"level": 25,
"lh_t": null,
"life_state": null,
"max_hero_hit": null,
"multi_kills": null,
"net_worth": 19909,
"obs": null,
"obs_left_log": null,
"obs_log": null,
"obs_placed": null,
"party_id": 0,
"party_size": 1,
"performance_others": null,
"permanent_buffs": null,
"pings": null,
"pred_vict": null,
"purchase": null,
"purchase_log": null,
"randomed": null,
"repicked": null,
"roshans_killed": null,
"rune_pickups": null,
"runes": null,
"runes_log": null,
"sen": null,
"sen_left_log": null,
"sen_log": null,
"sen_placed": null,
"stuns": null,
"teamfight_participation": null,
"times": null,
"tower_damage": 0,
"towers_killed": null,
"xp_per_min": 770,
"xp_reasons": null,
"xp_t": null,
"personaname": "***CAP***",
"name": null,
"last_login": null,
"radiant_win": false,
"start_time": 1616976674,
"duration": 2343,
"cluster": 251,
"lobby_type": 7,
"game_mode": 22,
"is_contributor": false,
"patch": 47,
"region": 15,
"isRadiant": true,
"win": 0,
"lose": 1,
"total_gold": 22102,
"total_xp": 30068,
"kills_per_min": 0.3585147247119078,
"kda": 2,
"abandons": 0,
"rank_tier": 34,
"cosmetics": [],
"benchmarks": {
"gold_per_min": {
"raw": 566,
"pct": 0.5743944636678201
},
"xp_per_min": {
"raw": 770,
"pct": 0.7768166089965398
},
"kills_per_min": {
"raw": 0.3585147247119078,
"pct": 0.8737024221453287
},
"last_hits_per_min": {
"raw": 8.425096030729833,
"pct": 0.6591695501730104
},
"hero_damage_per_min": {
"raw": 920.5889884763124,
"pct": 0.71280276816609
},
"hero_healing_per_min": {
"raw": 0,
"pct": 0.870242214532872
},
"tower_damage": {
"raw": 0,
"pct": 0.10899653979238755
},
"stuns_per_min": {
"raw": 0,
"pct": 0
},
"lhten": {}
}
},
{
"match_id": 5915014243,
"player_slot": 1,
"ability_targets": null,
"ability_upgrades_arr": [
5372,
5370,
5372,
5370,
5372,
5370,
5371,
5372,
5371,
5372,
5371,
5371,
5370,
5372,
5371,
6811,
5371,
7148,
5370,
6657,
5370,
5372,
5371
],
"ability_uses": null,
"account_id": null,
"actions": null,
"additional_units": null,
"assists": 10,
"backpack_0": 216,
"backpack_1": 0,
"backpack_2": 0,
"backpack_3": null,
"buyback_log": null,
"camps_stacked": null,
"connection_log": null,
"creeps_stacked": null,
"damage": null,
"damage_inflictor": null,
"damage_inflictor_received": null,
"damage_taken": null,
"damage_targets": null,
"deaths": 9,
"denies": 1,
"dn_t": null,
"firstblood_claimed": null,
"gold": 266,
"gold_per_min": 395,
"gold_reasons": null,
"gold_spent": 13010,
"gold_t": null,
"hero_damage": 20856,
"hero_healing": 0,
"hero_hits": null,
"hero_id": 74,
"item_0": 50,
"item_1": 100,
"item_2": 116,
"item_3": 98,
"item_4": 0,
"item_5": 34,
"item_neutral": 675,
"item_uses": null,
"kill_streaks": null,
"killed": null,
"killed_by": null,
"kills": 9,
"kills_log": null,
"lane_pos": null,
"last_hits": 148,
"leaver_status": 0,
"level": 23,
"lh_t": null,
"life_state": null,
"max_hero_hit": null,
"multi_kills": null,
"net_worth": 12376,
"obs": null,
"obs_left_log": null,
"obs_log": null,
"obs_placed": null,
"party_id": 1,
"party_size": 1,
"performance_others": null,
"permanent_buffs": null,
"pings": null,
"pred_vict": null,
"purchase": null,
"purchase_log": null,
"randomed": null,
"repicked": null,
"roshans_killed": null,
"rune_pickups": null,
"runes": null,
"runes_log": null,
"sen": null,
"sen_left_log": null,
"sen_log": null,
"sen_placed": null,
"stuns": null,
"teamfight_participation": null,
"times": null,
"tower_damage": 1383,
"towers_killed": null,
"xp_per_min": 638,
"xp_reasons": null,
"xp_t": null,
"radiant_win": false,
"start_time": 1616976674,
"duration": 2343,
"cluster": 251,
"lobby_type": 7,
"game_mode": 22,
"is_contributor": false,
"patch": 47,
"region": 15,
"isRadiant": true,
"win": 0,
"lose": 1,
"total_gold": 15424,
"total_xp": 24913,
"kills_per_min": 0.23047375160051217,
"kda": 1,
"abandons": 0,
"rank_tier": null,
"cosmetics": [],
"benchmarks": {
"gold_per_min": {
"raw": 395,
"pct": 0.3058823529411765
},
"xp_per_min": {
"raw": 638,
"pct": 0.5195046439628483
},
"kills_per_min": {
"raw": 0.23047375160051214,
"pct": 0.6520123839009287
},
"last_hits_per_min": {
"raw": 3.7900128040973113,
"pct": 0.3622291021671827
},
"hero_damage_per_min": {
"raw": 534.0845070422536,
"pct": 0.3510835913312694
},
"hero_healing_per_min": {
"raw": 0,
"pct": 0.8055727554179567
},
"tower_damage": {
"raw": 1383,
"pct": 0.3801857585139319
},
"stuns_per_min": {
"raw": 0,
"pct": 0.0006191950464396285
},
"lhten": {}
}
},
{
"match_id": 5915014243,
"player_slot": 2,
"ability_targets": null,
"ability_upgrades_arr": [
5347,
5345,
5347,
5346,
5347,
5348,
5347,
5345,
5346,
5949,
5346,
5348,
5346,
6352,
5345,
5345
],
"ability_uses": null,
"account_id": 363315282,
"actions": null,
"additional_units": null,
"assists": 23,
"backpack_0": 0,
"backpack_1": 0,
"backpack_2": 0,
"backpack_3": null,
"buyback_log": null,
"camps_stacked": null,
"connection_log": null,
"creeps_stacked": null,
"damage": null,
"damage_inflictor": null,
"damage_inflictor_received": null,
"damage_taken": null,
"damage_targets": null,
"deaths": 8,
"denies": 0,
"dn_t": null,
"firstblood_claimed": null,
"gold": 941,
"gold_per_min": 229,
"gold_reasons": null,
"gold_spent": 7755,
"gold_t": null,
"hero_damage": 15394,
"hero_healing": 400,
"hero_hits": null,
"hero_id": 68,
"item_0": 34,
"item_1": 102,
"item_2": 43,
"item_3": 180,
"item_4": 0,
"item_5": 38,
"item_neutral": 357,
"item_uses": null,
"kill_streaks": null,
"killed": null,
"killed_by": null,
"kills": 4,
"kills_log": null,
"lane_pos": null,
"last_hits": 27,
"leaver_status": 0,
"level": 17,
"lh_t": null,
"life_state": null,
"max_hero_hit": null,
"multi_kills": null,
"net_worth": 6241,
"obs": null,
"obs_left_log": null,
"obs_log": null,
"obs_placed": null,
"party_id": 2,
"party_size": 1,
"performance_others": null,
"permanent_buffs": [
{
"permanent_buff": 6,
"stack_count": 1
},
{
"permanent_buff": 12,
"stack_count": 0
}
],
"pings": null,
"pred_vict": null,
"purchase": null,
"purchase_log": null,
"randomed": null,
"repicked": null,
"roshans_killed": null,
"rune_pickups": null,
"runes": null,
"runes_log": null,
"sen": null,
"sen_left_log": null,
"sen_log": null,
"sen_placed": null,
"stuns": null,
"teamfight_participation": null,
"times": null,
"tower_damage": 51,
"towers_killed": null,
"xp_per_min": 371,
"xp_reasons": null,
"xp_t": null,
"personaname": ".",
"name": null,
"last_login": null,
"radiant_win": false,
"start_time": 1616976674,
"duration": 2343,
"cluster": 251,
"lobby_type": 7,
"game_mode": 22,
"is_contributor": false,
"patch": 47,
"region": 15,
"isRadiant": true,
"win": 0,
"lose": 1,
"total_gold": 8942,
"total_xp": 14487,
"kills_per_min": 0.10243277848911653,
"kda": 3,
"abandons": 0,
"rank_tier": 41,
"cosmetics": [],
"benchmarks": {
"gold_per_min": {
"raw": 229,
"pct": 0.09527170077628794
},
"xp_per_min": {
"raw": 371,
"pct": 0.23429781227946367
},
"kills_per_min": {
"raw": 0.10243277848911653,
"pct": 0.44318983768525055
},
"last_hits_per_min": {
"raw": 0.6914212548015365,
"pct": 0.25335215243472126
},
"hero_damage_per_min": {
"raw": 394.2125480153649,
"pct": 0.3697953422724065
},
"hero_healing_per_min": {
"raw": 10.243277848911651,
"pct": 0.6725476358503881
},
"tower_damage": {
"raw": 51,
"pct": 0.31898376852505295
},
"stuns_per_min": {
"raw": 0,
"pct": 0.007057163020465773
},
"lhten": {}
}
},
{
"match_id": 5915014243,
"player_slot": 3,
"ability_targets": null,
"ability_upgrades_arr": [
5076,
5075,
5075,
5076,
5075,
5077,
5074,
5075,
5076,
5076,
5074,
5077,
5074,
5074,
5931,
6564,
5077,
408
],
"ability_uses": null,
"account_id": null,
"actions": null,
"additional_units": null,
"assists": 15,
"backpack_0": 0,
"backpack_1": 0,
"backpack_2": 290,
"backpack_3": null,
"buyback_log": null,
"camps_stacked": null,
"connection_log": null,
"creeps_stacked": null,
"damage": null,
"damage_inflictor": null,
"damage_inflictor_received": null,
"damage_taken": null,
"damage_targets": null,
"deaths": 10,
"denies": 2,
"dn_t": null,
"firstblood_claimed": null,
"gold": 775,
"gold_per_min": 300,
"gold_reasons": null,
"gold_spent": 12020,
"gold_t": null,
"hero_damage": 13118,
"hero_healing": 400,
"hero_hits": null,
"hero_id": 14,
"item_0": 12,
"item_1": 210,
"item_2": 36,
"item_3": 102,
"item_4": 216,
"item_5": 214,
"item_neutral": 574,
"item_uses": null,
"kill_streaks": null,
"killed": null,
"killed_by": null,
"kills": 3,
"kills_log": null,
"lane_pos": null,
"last_hits": 72,
"leaver_status": 0,
"level": 21,
"lh_t": null,
"life_state": null,
"max_hero_hit": null,
"multi_kills": null,
"net_worth": 9710,
"obs": null,
"obs_left_log": null,
"obs_log": null,
"obs_placed": null,
"party_id": 3,
"party_size": 1,
"performance_others": null,
"permanent_buffs": [
{
"permanent_buff": 4,
"stack_count": 12
},
{
"permanent_buff": 12,
"stack_count": 0
}
],
"pings": null,
"pred_vict": null,
"purchase": null,
"purchase_log": null,
"randomed": null,
"repicked": null,
"roshans_killed": null,
"rune_pickups": null,
"runes": null,
"runes_log": null,
"sen": null,
"sen_left_log": null,
"sen_log": null,
"sen_placed": null,
"stuns": null,
"teamfight_participation": null,
"times": null,
"tower_damage": 0,
"towers_killed": null,
"xp_per_min": 520,
"xp_reasons": null,
"xp_t": null,
"radiant_win": false,
"start_time": 1616976674,
"duration": 2343,
"cluster": 251,
"lobby_type": 7,
"game_mode": 22,
"is_contributor": false,
"patch": 47,
"region": 15,
"isRadiant": true,
"win": 0,
"lose": 1,
"total_gold": 11715,
"total_xp": 20306,
"kills_per_min": 0.0768245838668374,
"kda": 1,
"abandons": 0,
"rank_tier": null,
"cosmetics": [],
"benchmarks": {
"gold_per_min": {
"raw": 300,
"pct": 0.34802362562471606
},
"xp_per_min": {
"raw": 520,
"pct": 0.5393003180372558
},
"kills_per_min": {
"raw": 0.07682458386683738,
"pct": 0.20717855520218081
},
"last_hits_per_min": {
"raw": 1.8437900128040972,
"pct": 0.5338482507950931
},
"hero_damage_per_min": {
"raw": 335.9282970550576,
"pct": 0.2789641072239891
},
"hero_healing_per_min": {
"raw": 10.243277848911651,
"pct": 0.6551567469332121
},
"tower_damage": {
"raw": 0,
"pct": 0.33303044070876875
},
"stuns_per_min": {
"raw": 0,
"pct": 0.0013630168105406633
},
"lhten": {}
}
},
{
"match_id": 5915014243,
"player_slot": 4,
"ability_targets": null,
"ability_upgrades_arr": [
5027,
5028,
5027,
5028,
5028,
5030,
5027,
5027,
5028,
5918,
5029,
5030,
5029,
5029,
5029,
5906,
5030,
7021
],
"ability_uses": null,
"account_id": null,
"actions": null,
"additional_units": null,
"assists": 7,
"backpack_0": 39,
"backpack_1": 34,
"backpack_2": 0,
"backpack_3": null,
"buyback_log": null,
"camps_stacked": null,
"connection_log": null,
"creeps_stacked": null,
"damage": null,
"damage_inflictor": null,
"damage_inflictor_received": null,
"damage_taken": null,
"damage_targets": null,
"deaths": 9,
"denies": 1,
"dn_t": null,
"firstblood_claimed": null,
"gold": 228,
"gold_per_min": 362,
"gold_reasons": null,
"gold_spent": 13670,
"gold_t": null,
"hero_damage": 7579,
"hero_healing": 488,
"hero_hits": null,
"hero_id": 8,
"item_0": 50,
"item_1": 166,
"item_2": 154,
"item_3": 21,
"item_4": 60,
"item_5": 23,
"item_neutral": 376,
"item_uses": null,
"kill_streaks": null,
"killed": null,
"killed_by": null,
"kills": 6,
"kills_log": null,
"lane_pos": null,
"last_hits": 187,
"leaver_status": 0,
"level": 22,
"lh_t": null,
"life_state": null,
"max_hero_hit": null,
"multi_kills": null,
"net_worth": 12018,
"obs": null,
"obs_left_log": null,
"obs_log": null,
"obs_placed": null,
"party_id": 4,
"party_size": 1,
"performance_others": null,
"permanent_buffs": [
{
"permanent_buff": 6,
"stack_count": 2
}
],
"pings": null,
"pred_vict": null,
"purchase": null,
"purchase_log": null,
"randomed": null,
"repicked": null,
"roshans_killed": null,
"rune_pickups": null,
"runes": null,
"runes_log": null,
"sen": null,
"sen_left_log": null,
"sen_log": null,
"sen_placed": null,
"stuns": null,
"teamfight_participation": null,
"times": null,
"tower_damage": 169,
"towers_killed": null,
"xp_per_min": 581,
"xp_reasons": null,
"xp_t": null,
"radiant_win": false,
"start_time": 1616976674,
"duration": 2343,
"cluster": 251,
"lobby_type": 7,
"game_mode": 22,
"is_contributor": false,
"patch": 47,
"region": 15,
"isRadiant": true,
"win": 0,
"lose": 1,
"total_gold": 14136,
"total_xp": 22688,
"kills_per_min": 0.1536491677336748,
"kda": 1,
"abandons": 0,
"rank_tier": null,
"cosmetics": [],
"benchmarks": {
"gold_per_min": {
"raw": 362,
"pct": 0.04137039431157078
},
"xp_per_min": {
"raw": 581,
"pct": 0.20749838396897222
},
"kills_per_min": {
"raw": 0.15364916773367476,
"pct": 0.3076923076923077
},
"last_hits_per_min": {
"raw": 4.788732394366197,
"pct": 0.056884292178409825
},
"hero_damage_per_min": {
"raw": 194.0845070422535,
"pct": 0.01874595992243051
},
"hero_healing_per_min": {
"raw": 12.496798975672215,
"pct": 0.05106658047834518
},
"tower_damage": {
"raw": 169,
"pct": 0.12217194570135746
},
"stuns_per_min": {
"raw": 0,
"pct": 0.6845507433742728
},
"lhten": {}
}
},
{
"match_id": 5915014243,
"player_slot": 128,
"ability_targets": null,
"ability_upgrades_arr": [
5033,
5032,
5032,
5031,
5032,
5035,
5032,
5033,
5033,
5939,
5033,
5035,
5031,
5031,
6385,
5031,
5035,
6080
],
"ability_uses": null,
"account_id": null,
"actions": null,
"additional_units": null,
"assists": 14,
"backpack_0": 0,
"backpack_1": 0,
"backpack_2": 0,
"backpack_3": null,
"buyback_log": null,
"camps_stacked": null,
"connection_log": null,
"creeps_stacked": null,
"damage": null,
"damage_inflictor": null,
"damage_inflictor_received": null,
"damage_taken": null,
"damage_targets": null,
"deaths": 7,
"denies": 6,
"dn_t": null,
"firstblood_claimed": null,
"gold": 1727,
"gold_per_min": 548,
"gold_reasons": null,
"gold_spent": 20300,
"gold_t": null,
"hero_damage": 22845,
"hero_healing": 0,
"hero_hits": null,
"hero_id": 23,
"item_0": 226,
"item_1": 141,
"item_2": 73,
"item_3": 108,
"item_4": 36,
"item_5": 50,
"item_neutral": 686,
"item_uses": null,
"kill_streaks": null,
"killed": null,
"killed_by": null,
"kills": 6,
"kills_log": null,
"lane_pos": null,
"last_hits": 263,
"leaver_status": 0,
"level": 23,
"lh_t": null,
"life_state": null,
"max_hero_hit": null,
"multi_kills": null,
"net_worth": 18977,
"obs": null,
"obs_left_log": null,
"obs_log": null,
"obs_placed": null,
"party_id": 5,
"party_size": 1,
"performance_others": null,
"permanent_buffs": [
{
"permanent_buff": 12,
"stack_count": 0
}
],
"pings": null,
"pred_vict": null,
"purchase": null,
"purchase_log": null,
"randomed": null,
"repicked": null,
"roshans_killed": null,
"rune_pickups": null,
"runes": null,
"runes_log": null,
"sen": null,
"sen_left_log": null,
"sen_log": null,
"sen_placed": null,
"stuns": null,
"teamfight_participation": null,
"times": null,
"tower_damage": 4296,
"towers_killed": null,
"xp_per_min": 646,
"xp_reasons": null,
"xp_t": null,
"radiant_win": false,
"start_time": 1616976674,
"duration": 2343,
"cluster": 251,
"lobby_type": 7,
"game_mode": 22,
"is_contributor": false,
"patch": 47,
"region": 15,
"isRadiant": false,
"win": 1,
"lose": 0,
"total_gold": 21399,
"total_xp": 25226,
"kills_per_min": 0.1536491677336748,
"kda": 2,
"abandons": 0,
"rank_tier": null,
"cosmetics": [],
"benchmarks": {
"gold_per_min": {
"raw": 548,
"pct": 0.621268656716418
},
"xp_per_min": {
"raw": 646,
"pct": 0.4962686567164179
},
"kills_per_min": {
"raw": 0.15364916773367476,
"pct": 0.48134328358208955
},
"last_hits_per_min": {
"raw": 6.734955185659411,
"pct": 0.5373134328358209
},
"hero_damage_per_min": {
"raw": 585.0192061459668,
"pct": 0.46455223880597013
},
"hero_healing_per_min": {
"raw": 0,
"pct": 0.7686567164179104
},
"tower_damage": {
"raw": 4296,
"pct": 0.7835820895522388
},
"stuns_per_min": {
"raw": 0,
"pct": 0
},
"lhten": {}
}
},
{
"match_id": 5915014243,
"player_slot": 129,
"ability_targets": null,
"ability_upgrades_arr": [
5044,
5045,
5044,
5046,
5047,
5044,
5044,
5046,
5046,
465,
5046,
5047,
5045,
5045,
540,
5045,
5047,
541
],
"ability_uses": null,
"account_id": null,
"actions": null,
"additional_units": null,
"assists": 14,
"backpack_0": 0,
"backpack_1": 0,
"backpack_2": 0,
"backpack_3": null,
"buyback_log": null,
"camps_stacked": null,
"connection_log": null,
"creeps_stacked": null,
"damage": null,
"damage_inflictor": null,
"damage_inflictor_received": null,
"damage_taken": null,
"damage_targets": null,
"deaths": 12,
"denies": 2,
"dn_t": null,
"firstblood_claimed": null,
"gold": 814,
"gold_per_min": 325,
"gold_reasons": null,
"gold_spent": 11485,
"gold_t": null,
"hero_damage": 13012,
"hero_healing": 0,
"hero_hits": null,
"hero_id": 26,
"item_0": 214,
"item_1": 1,
"item_2": 0,
"item_3": 235,
"item_4": 0,
"item_5": 0,
"item_neutral": 676,
"item_uses": null,
"kill_streaks": null,
"killed": null,
"killed_by": null,
"kills": 9,
"kills_log": null,
"lane_pos": null,
"last_hits": 31,
"leaver_status": 0,
"level": 21,
"lh_t": null,
"life_state": null,
"max_hero_hit": null,
"multi_kills": null,
"net_worth": 9554,
"obs": null,
"obs_left_log": null,
"obs_log": null,
"obs_placed": null,
"party_id": 6,
"party_size": 1,
"performance_others": null,
"permanent_buffs": [
{
"permanent_buff": 6,
"stack_count": 3
},
{
"permanent_buff": 7,
"stack_count": 9
}
],
"pings": null,
"pred_vict": null,
"purchase": null,
"purchase_log": null,
"randomed": null,
"repicked": null,
"roshans_killed": null,
"rune_pickups": null,
"runes": null,
"runes_log": null,
"sen": null,
"sen_left_log": null,
"sen_log": null,
"sen_placed": null,
"stuns": null,
"teamfight_participation": null,
"times": null,
"tower_damage": 734,
"towers_killed": null,
"xp_per_min": 535,
"xp_reasons": null,
"xp_t": null,
"radiant_win": false,
"start_time": 1616976674,
"duration": 2343,
"cluster": 251,
"lobby_type": 7,
"game_mode": 22,
"is_contributor": false,
"patch": 47,
"region": 15,
"isRadiant": false,
"win": 1,
"lose": 0,
"total_gold": 12691,
"total_xp": 20891,
"kills_per_min": 0.23047375160051217,
"kda": 1,
"abandons": 0,
"rank_tier": null,
"cosmetics": [],
"benchmarks": {
"gold_per_min": {
"raw": 325,
"pct": 0.6527472527472528
},
"xp_per_min": {
"raw": 535,
"pct": 0.6835164835164835
},
"kills_per_min": {
"raw": 0.23047375160051214,
"pct": 0.9076923076923077
},
"last_hits_per_min": {
"raw": 0.793854033290653,
"pct": 0.29010989010989013
},
"hero_damage_per_min": {
"raw": 333.21382842509604,
"pct": 0.6628571428571428
},
"hero_healing_per_min": {
"raw": 0,
"pct": 0.6149450549450549
},
"tower_damage": {
"raw": 734,
"pct": 0.7265934065934065
},
"stuns_per_min": {
"raw": 0,
"pct": 0
},
"lhten": {}
}
},
{
"match_id": 5915014243,
"player_slot": 130,
"ability_targets": null,
"ability_upgrades_arr": [
5003,
5004,
5003,
7314,
5004,
5006,
5004,
5004,
5003,
6119,
7314,
5006,
7314,
7314,
6606,
5003,
5006,
6012,
6607
],
"ability_uses": null,
"account_id": null,
"actions": null,
"additional_units": null,
"assists": 13,
"backpack_0": 0,
"backpack_1": 0,
"backpack_2": 0,
"backpack_3": null,
"buyback_log": null,
"camps_stacked": null,
"connection_log": null,
"creeps_stacked": null,
"damage": null,
"damage_inflictor": null,
"damage_inflictor_received": null,
"damage_taken": null,
"damage_targets": null,
"deaths": 1,
"denies": 29,
"dn_t": null,
"firstblood_claimed": null,
"gold": 1375,
"gold_per_min": 860,
"gold_reasons": null,
"gold_spent": 32535,
"gold_t": null,
"hero_damage": 34915,
"hero_healing": 0,
"hero_hits": null,
"hero_id": 1,
"item_0": 145,
"item_1": 160,
"item_2": 63,
"item_3": 208,
"item_4": 147,
"item_5": 139,
"item_neutral": 362,
"item_uses": null,
"kill_streaks": null,
"killed": null,
"killed_by": null,
"kills": 15,
"kills_log": null,
"lane_pos": null,
"last_hits": 470,
"leaver_status": 0,
"level": 29,
"lh_t": null,
"life_state": null,
"max_hero_hit": null,
"multi_kills": null,
"net_worth": 32595,
"obs": null,
"obs_left_log": null,
"obs_log": null,
"obs_placed": null,
"party_id": 7,
"party_size": 1,
"performance_others": null,
"permanent_buffs": [
{
"permanent_buff": 1,
"stack_count": 0
}
],
"pings": null,
"pred_vict": null,
"purchase": null,
"purchase_log": null,
"randomed": null,
"repicked": null,
"roshans_killed": null,
"rune_pickups": null,
"runes": null,
"runes_log": null,
"sen": null,
"sen_left_log": null,
"sen_log": null,
"sen_placed": null,
"stuns": null,
"teamfight_participation": null,
"times": null,
"tower_damage": 12465,
"towers_killed": null,
"xp_per_min": 921,
"xp_reasons": null,
"xp_t": null,
"radiant_win": false,
"start_time": 1616976674,
"duration": 2343,
"cluster": 251,
"lobby_type": 7,
"game_mode": 22,
"is_contributor": false,
"patch": 47,
"region": 15,
"isRadiant": false,
"win": 1,
"lose": 0,
"total_gold": 33583,
"total_xp": 35965,
"kills_per_min": 0.38412291933418696,
"kda": 14,
"abandons": 0,
"rank_tier": null,
"cosmetics": [],
"benchmarks": {
"gold_per_min": {
"raw": 860,
"pct": 0.9574235807860262
},
"xp_per_min": {
"raw": 921,
"pct": 0.9246724890829694
},
"kills_per_min": {
"raw": 0.3841229193341869,
"pct": 0.9213973799126638
},
"last_hits_per_min": {
"raw": 12.03585147247119,
"pct": 0.8679039301310044
},
"hero_damage_per_min": {
"raw": 894.1101152368758,
"pct": 0.8482532751091703
},
"hero_healing_per_min": {
"raw": 0,
"pct": 0.980349344978166
},
"tower_damage": {
"raw": 12465,
"pct": 0.7860262008733624
},
"stuns_per_min": {
"raw": 0,
"pct": 0.014192139737991267
},
"lhten": {}
}
},
{
"match_id": 5915014243,
"player_slot": 131,
"ability_targets": null,
"ability_upgrades_arr": [
7322,
5566,
7322,
5565,
7322,
5568,
7322,
5566,
5566,
414,
5565,
5568,
5566,
5565,
6411,
5565,
5568,
6194
],
"ability_uses": null,
"account_id": null,
"actions": null,
"additional_units": null,
"assists": 14,
"backpack_0": 11,
"backpack_1": 0,
"backpack_2": 0,
"backpack_3": null,
"buyback_log": null,
"camps_stacked": null,
"connection_log": null,
"creeps_stacked": null,
"damage": null,
"damage_inflictor": null,
"damage_inflictor_received": null,
"damage_taken": null,
"damage_targets": null,
"deaths": 7,
"denies": 11,
"dn_t": null,
"firstblood_claimed": null,
"gold": 2710,
"gold_per_min": 443,
"gold_reasons": null,
"gold_spent": 14255,
"gold_t": null,
"hero_damage": 13953,
"hero_healing": 0,
"hero_hits": null,
"hero_id": 100,
"item_0": 50,
"item_1": 226,
"item_2": 267,
"item_3": 36,
"item_4": 168,
"item_5": 73,
"item_neutral": 638,
"item_uses": null,
"kill_streaks": null,
"killed": null,
"killed_by": null,
"kills": 7,
"kills_log": null,
"lane_pos": null,
"last_hits": 176,
"leaver_status": 0,
"level": 23,
"lh_t": null,
"life_state": null,
"max_hero_hit": null,
"multi_kills": null,
"net_worth": 15780,
"obs": null,
"obs_left_log": null,
"obs_log": null,
"obs_placed": null,
"party_id": 8,
"party_size": 1,
"performance_others": null,
"permanent_buffs": null,
"pings": null,
"pred_vict": null,
"purchase": null,
"purchase_log": null,
"randomed": null,
"repicked": null,
"roshans_killed": null,
"rune_pickups": null,
"runes": null,
"runes_log": null,
"sen": null,
"sen_left_log": null,
"sen_log": null,
"sen_placed": null,
"stuns": null,
"teamfight_participation": null,
"times": null,
"tower_damage": 2992,
"towers_killed": null,
"xp_per_min": 621,
"xp_reasons": null,
"xp_t": null,
"radiant_win": false,
"start_time": 1616976674,
"duration": 2343,
"cluster": 251,
"lobby_type": 7,
"game_mode": 22,
"is_contributor": false,
"patch": 47,
"region": 15,
"isRadiant": false,
"win": 1,
"lose": 0,
"total_gold": 17299,
"total_xp": 24250,
"kills_per_min": 0.1792573623559539,
"kda": 2,
"abandons": 0,
"rank_tier": null,
"cosmetics": [],
"benchmarks": {
"gold_per_min": {
"raw": 443,
"pct": 0.9187358916478555
},
"xp_per_min": {
"raw": 621,
"pct": 0.8261851015801355
},
"kills_per_min": {
"raw": 0.1792573623559539,
"pct": 0.781038374717833
},
"last_hits_per_min": {
"raw": 4.507042253521127,
"pct": 0.9593679458239278
},
"hero_damage_per_min": {
"raw": 357.31113956466066,
"pct": 0.49887133182844245
},
"hero_healing_per_min": {
"raw": 0,
"pct": 0.6275395033860045
},
"tower_damage": {
"raw": 2992,
"pct": 0.945823927765237
},
"stuns_per_min": {
"raw": 0,
"pct": 0.002257336343115124
},
"lhten": {}
}
},
{
"match_id": 5915014243,
"player_slot": 132,
"ability_targets": null,
"ability_upgrades_arr": [
5080,
5078,
5080,
5079,
5080,
5081,
5078,
5078,
5078,
6034,
5080,
5081,
5079,
5079,
6003,
5079,
5081
],
"ability_uses": null,
"account_id": null,
"actions": null,
"additional_units": null,
"assists": 16,
"backpack_0": 42,
"backpack_1": 0,
"backpack_2": 0,
"backpack_3": null,
"buyback_log": null,
"camps_stacked": null,
"connection_log": null,
"creeps_stacked": null,
"damage": null,
"damage_inflictor": null,
"damage_inflictor_received": null,
"damage_taken": null,
"damage_targets": null,
"deaths": 9,
"denies": 4,
"dn_t": null,
"firstblood_claimed": null,
"gold": 1402,
"gold_per_min": 338,
"gold_reasons": null,
"gold_spent": 11245,
"gold_t": null,
"hero_damage": 9194,
"hero_healing": 0,
"hero_hits": null,
"hero_id": 27,
"item_0": 108,
"item_1": 254,
"item_2": 232,
"item_3": 216,
"item_4": 34,
"item_5": 214,
"item_neutral": 0,
"item_uses": null,
"kill_streaks": null,
"killed": null,
"killed_by": null,
"kills": 6,
"kills_log": null,
"lane_pos": null,
"last_hits": 60,
"leaver_status": 0,
"level": 19,
"lh_t": null,
"life_state": null,
"max_hero_hit": null,
"multi_kills": null,
"net_worth": 11112,
"obs": null,
"obs_left_log": null,
"obs_log": null,
"obs_placed": null,
"party_id": 9,
"party_size": 1,
"performance_others": null,
"permanent_buffs": null,
"pings": null,
"pred_vict": null,
"purchase": null,
"purchase_log": null,
"randomed": null,
"repicked": null,
"roshans_killed": null,
"rune_pickups": null,
"runes": null,
"runes_log": null,
"sen": null,
"sen_left_log": null,
"sen_log": null,
"sen_placed": null,
"stuns": null,
"teamfight_participation": null,
"times": null,
"tower_damage": 2975,
"towers_killed": null,
"xp_per_min": 421,
"xp_reasons": null,
"xp_t": null,
"radiant_win": false,
"start_time": 1616976674,
"duration": 2343,
"cluster": 251,
"lobby_type": 7,
"game_mode": 22,
"is_contributor": false,
"patch": 47,
"region": 15,
"isRadiant": false,
"win": 1,
"lose": 0,
"total_gold": 13198,
"total_xp": 16440,
"kills_per_min": 0.1536491677336748,
"kda": 2,
"abandons": 0,
"rank_tier": null,
"cosmetics": [],
"benchmarks": {
"gold_per_min": {
"raw": 338,
"pct": 0.5505716798592788
},
"xp_per_min": {
"raw": 421,
"pct": 0.41072999120492526
},
"kills_per_min": {
"raw": 0.15364916773367476,
"pct": 0.8390501319261213
},
"last_hits_per_min": {
"raw": 1.5364916773367476,
"pct": 0.3658751099384345
},
"hero_damage_per_min": {
"raw": 235.44174135723432,
"pct": 0.20580474934036938
},
"hero_healing_per_min": {
"raw": 0,
"pct": 0.565523306948109
},
"tower_damage": {
"raw": 2975,
"pct": 0.6086191732629728
},
"stuns_per_min": {
"raw": 0,
"pct": 0
},
"lhten": {}
}
}
],
"patch": 47,
"region": 15,
"replay_url": "http://replay251.valve.net/570/5915014243_1182407340.dem.bz2"
}